directoryFinder-mac/__init__.py
directoryFinder-mac/core.py
directoryFinder_mac/__init__.py
directoryFinder_mac/core.py
directoryfinder_mac-0.1.1.dist-info/licenses/LICENSE.md
directoryfinder_mac-0.1.1.dist-info/METADATA
directoryfinder_mac-0.1.1.dist-info/WHEEL
directoryfinder_mac-0.1.1.dist-info/top_level.txt
directoryfinder_mac-0.1.1.dist-info/RECORD
