Metadata-Version: 2.4
Name: directoryFinder-mac
Version: 0.1.1
Summary: Find files/folders in specific macOS directories using fuzzy search.
Home-page: https://github.com/nagaajau/directoryFinder-mac
Author: Polisetty Naga Ajay
Author-email: polisettynagaajay5103@gmail.com
Classifier: Programming Language :: Python :: 3
Classifier: Operating System :: MacOS
Classifier: License :: OSI Approved :: MIT License
Requires-Python: >=3.6
License-File: LICENSE.md
Dynamic: author
Dynamic: author-email
Dynamic: classifier
Dynamic: description
Dynamic: description-content-type
Dynamic: home-page
Dynamic: license-file
Dynamic: requires-python
Dynamic: summary
